{"contracts_nft contract_nft actions_delprchsreq.a.md":"315e66b5","contracts_nft contract_nft actions_fhglobalshr.md":"ac30e113","contracts_nft contract_nft actions_globalshare.md":"cebb06fd","contracts_nft contract_nft actions_issue.b.md":"97bd60c5","contracts_nft contract_nft actions_issue.md":"557bf9b6","contracts_nft contract_nft actions_limitmint.md":"23dbb8ec","contracts_nft contract_nft actions_mgrnfts.md":"6e89d199","contracts_nft contract_nft actions_mgrfactories.md":"c12aba5e","api_rest_get-block.md":"1f3b64d5","api_rest_get-table-rows.md":"fd52ef62","contracts_nft contract_nft actions_cancelresell.md":"e6a1daf0","contracts_nft contract_nft actions_lckfactory.md":"7e661d64","api_common-tables.md":"229b4db3","contracts_nft contract_nft actions_migration.md":"996cabdb","contracts_kyc contract_kyc-tables.md":"020b8c4c","contracts_nft contract_nft actions_addgrpfcts.md":"52152fdb","contracts_kyc contract_kyc actions_removekyc.md":"8aa71ae6","contracts_kyc contract_kyc actions_removekycpro.md":"dd8c15dc","contracts_nft contract_nft actions_buy.md":"b9ce14db","contracts_kyc contract_kyc actions_updatekyc.md":"b8bf02cd","api_rest_get-currency-balance.md":"49e8a30d","api_rest_get-table-by-scope.md":"ea68c876","contracts_nft contract_nft actions_create.md":"dfa11b58","contracts_nft contract_nft actions_authminter.md":"c1075485","contracts_nft contract_nft actions_authmint.b.md":"ab455ad4","api_rest_get-account.md":"3528472f","contracts_nft contract_nft actions_clrmintst.md":"8a62c414","contracts_kyc contract_kyc-policy.md":"1e94e10d","contracts_nft contract_nft actions_create.b.md":"5dbf8cdc","api_index.md":"e099fba6","contracts_kyc contract_kyc actions_togglekyc.md":"10a23d4f","contracts_nft contract_nft actions_deletegrp.md":"96fbd02f","contracts_nft contract_nft actions_creategrp.md":"49454998","contracts_nft contract_nft actions_recall.md":"3d94b7db","api_rest_get-abi.md":"5be772f2","contracts_kyc contract_kyc actions_registerkyc.md":"f4c640b5","contracts_nft contract_nft actions_burn.md":"7a9a87a8","contracts_nft contract_nft actions_activers.md":"a2af8228","contracts_system contract_system actions_newnonebact.md":"e9dd9080","api_rest_get-info.md":"2fd4277b","contracts_system contract_system actions_revokepred.md":"cee7cf98","contracts_system contract_system actions_undelegatebw.md":"12c209dd","contracts_system contract_eba-non-eba-accounts.md":"1902014f","contracts_system contract_data-structures-overview.md":"a1ac4637","contracts_system contract_system actions_refundram.md":"922c2fc0","contracts_system contract_overview.md":"00a79b53","contracts_system contract_know-your-client.md":"d8ac6a30","contracts_nft contract_nft actions_purchase.a.md":"a4c05b1b","contracts_nft contract_nft actions_settrnfwin.a.md":"24bbe8b0","contracts_nft contract_nft actions_updategrp.md":"1fcf25fb","contracts_nft contract_nft actions_transfer.md":"1b5e56e2","contracts_token contract_token_tables.md":"09815695","contracts_user group contract_user group actions_adduser.md":"bcb8ea20","contracts_user group contract_user group actions_rmuser.md":"a8d9cb46","contracts_user group contract_user group actions_clear.md":"d1523dfe","contracts_user group contract_user group actions_create.md":"f757eabc","contracts_user group contract_user group actions_setmeta.md":"14549c19","contracts_user group contract_user-group-tables.md":"7e34e39c","contracts_user group contract_overview.md":"91bf07de","contracts_index.md":"c36eb85a","guides_basics_using-cleos.md":"ed1e118f","guides_building token factories_creatingmetadata.md":"76e1dfed","guides_building token factories_firsttokenfactory.md":"131f24fe","guides_building token factories_introduction.md":"d8302650","guides_building token factories_mintingyourfirstuniq.md":"70a2d7af","guides_cdt_compile-a-contract.md":"8db06740","guides_building token factories_yourdevelopmentenv.md":"09ca3b87","guides_cdt_create-a-contract.md":"7955e1a2","guides_integrating ultra_requesting-a-client_id.md":"8f0384db","guides_integrating ultra_use-ultra-unreal.md":"cd05eb0a","guides_smart contracts_2.setup.md":"19557ca9","guides_smart contracts_3.compile.md":"00f660f9","guides_nftapi_introduction.md":"c62e601b","guides_ultra specific_faucet.md":"8f0092cf","guides_docker_environments.md":"87c4a3cd","guides_ultra uniq discord bot_running-the-bot.md":"04b8987a","contracts_nft contract_overview.md":"9ff49f56","guides_docker_building-smart-contracts.md":"1eb1c050","contracts_system contract_power-bandwidth-staking.md":"1afbb7a8","contracts_system contract_system actions_allowpred.md":"92c49d96","contracts_system contract_ram-market.md":"05897966","guides_uniq variants_examples_example-project.md":"7691347c","contracts_nft contract_nft actions_setnftmgrflg.md":"3214c1dd","contracts_nft contract_nft actions_rmgrpfcts.md":"cc7976fe","contracts_nft contract_nft actions_setconrecv.md":"cad6f36e","contracts_nft contract_nft actions_setdflttkn.md":"0f091a3a","contracts_nft contract_nft actions_setmeta.b.md":"18ad2e29","contracts_nft contract_nft actions_setmeta.md":"abf180de","contracts_nft contract_nft actions_setstatus.md":"5e8d48c1","contracts_nft contract_nft actions_setprchsreq.a.md":"6ccb1622","contracts_nft contract_nft actions_setsharelim.md":"6c544216","contracts_nft contract_nft actions_settknmeta.md":"f3ec3ba4","contracts_nft contract_nft actions_settfflag.md":"183997da","contracts_nft contract_nft actions_settrdwin.a.md":"a65719a9","guides_smart contracts_4.deploy.md":"e3acaae2","guides_smart contracts_5.transact.md":"8d9b272c","guides_ultra specific_request-fungible-token.md":"1023d685","guides_ultra uniq discord bot_environment-variables.md":"5a687f36","guides_ultra uniq discord bot_installing-the-client.md":"27cf8946","guides_ultra uniq discord bot_installing-the-server.md":"91f1cc9e","guides_ultra uniq discord bot_introduction.md":"ac54dc1d","guides_ultra uniq discord bot_setup.md":"f7480677","guides_uniq avatar_introduction.md":"e7576dd6","guides_uniq avatar_setavatar.md":"d554c936","guides_integrating ultra_getting-started.md":"d2f4be07","guides_integrating ultra_ultra-sso-integration-guide.md":"81f9dc4d","contracts_system contract_system actions_buyram.md":"14a84f2d","contracts_system contract_system actions_newebact.md":"07b602ac","guides_nftapi_errors.md":"d9d2003b","guides_smart contracts_1.index.md":"7fab23ef","guides_docker_nodeos.md":"86c0154e","guides_docker_obtaining-tokens-locally.md":"2e6e57b8","guides_integrating ultra_use-ultra-unity.md":"cad96e63","guides_docker_development-environment.md":"40de76d0","guides_cdt_index.md":"4e898a2a","guides_docker_index.md":"c091b55e","guides_game dev center_7. assemble-game-builds.md":"0211f185","guides_game dev center_9. set-branch.md":"f00244c7","guides_integrating ultra_get-ultra-unity.md":"97cc1095","guides_ultra specific_token-swap.md":"39ef9c56","contracts_nft contract_nft-tables.md":"feab3d91","guides_nftapi_subscriptions.md":"9a5ea698","guides_nftapi_queries.md":"986e7288","guides_wallet extension_detect-wallet.md":"3a5fbb85","guides_wallet extension_errors.md":"fdd5aab4","guides_wallet extension_get-tokens-testnet.md":"d4700637","guides_wallet extension_import-private_key.md":"62d36986","guides_wallet extension_demo-application.md":"5478ae1b","guides_wallet extension_developer-resources.md":"bd44c0e0","guides_wallet extension_events.md":"b13d0d99","guides_wallet extension_installing-extension.md":"e549fd57","guides_wallet extension_signing_message.md":"f88ea53b","guides_index.md":"0039b956","guides_uwax_demo-application.md":"6f97a015","guides_wallet extension_index.md":"b3e1854f","guides_wallet extension_response-format.md":"286ff9f4","guides_uwax_developer-resources.md":"6c978437","guides_wallet extension_signing-transaction.md":"a3e21955","guides_wallet extension_stablishing-connection.md":"c7ff45dc","guides_uwax_custom-networks.md":"9fb17303","guides_uwax_import-private_key.md":"9836ca0b","guides_uwax_get-tokens-testnet.md":"e71607e8","guides_uwax_errors.md":"e7225629","guides_uwax_installing-extension.md":"2f750e5f","guides_uwax_events.md":"d4c287a3","guides_uwax_signing-transaction.md":"99b93240","guides_uwax_signing_message.md":"5303ac42","guides_uwax_stablishing-connection.md":"bf06e45d","guides_uwax_index.md":"64a7ba62","guides_uwax_response-format.md":"7277278b","learn_block producers_infrastructure_configuring-a-block-producer.md":"a2eecec5","learn_block producers_infrastructure_minimum-recommended-infrastructure.md":"04da1672","learn_block producers_infrastructure_understanding-the-config.md":"c9f455b4","index.md":"14609ed8","learn_block producers_infrastructure_block-producing-infrastructure.md":"25f8f4a2","learn_block producers_infrastructure_templates-for-config.md":"51f2924a","learn_block producers_launch procedures_adding-new-producers.md":"b6f38064","learn_block producers_launch procedures_core-concepts.md":"e582ca8d","learn_block producers_maintenance_account-administration.md":"f9a7a54f","learn_block producers_maintenance_backup-and-recovery.md":"d15050f3","learn_block producers_maintenance_launching-a-new-instance.md":"97ad2abc","learn_block producers_launch procedures_finishing-up.md":"1e6c6e17","learn_block producers_maintenance_multisignature-proposals.md":"c8e77898","learn_block producers_infrastructure_infrastructure-and-network-overview.md":"59aebe9a","guides_nftapi_authentication.md":"ec24e2a8","learn_block producers_launch procedures_activating-the-chain.md":"99174455","learn_block producers_launch procedures_registering-block-producers.md":"cdbb9d44","learn_block producers_maintenance_system-contract-upgrade.md":"6ba38b4f","contracts_system contract_predicate-system.md":"0eefce4d","contracts_system contract_system actions_buyrambytes.md":"4daef4d8","contracts_nft contract_nft actions_resell.md":"aa39c7c6","contracts_token contract_token actions_create.md":"dd7e0b59","learn_block producers_maintenance_upgrade-procedures.md":"e3478886","learn_block producers_launch procedures_resigning-eosio-and-system-accounts.md":"3778c1d3","guides_uniq variants_uniq-default-metadata.md":"2a536868","guides_basics_introduction.md":"f667de55","guides_basics_create-a-testnet-account.md":"79c166ee","contracts_system contract_system actions_delegatebw.md":"8d7cea66","guides_uniq variants_index.md":"5d1d116c","contracts_token contract_token actions_transfer.md":"9ad509a4","guides_uniq variants_examples_on-issue.md":"e87e58de","guides_uniq variants_examples_variant-example-use-cases.md":"086e2a4a","guides_integrating ultra_ultra-unreal-openid-guide.md":"ce3fbe39","guides_integrating ultra_get-ultra-unreal.md":"3e02225f","guides_uniq variants_common-metadata-concepts.md":"e9c87c2d","guides_uniq variants_factory-metadata.md":"3e1bafd7","guides_game dev center_5. declaring-a-game.md":"f6876a39","guides_uniq variants_faq.md":"51fdd88b","guides_uniq variants_organizing-metadata.md":"c7cf1788","contracts_token contract_token actions_retire.md":"b7cb783f","guides_game dev center_1. introduction.md":"c8e7c9a9","contracts_nft contract_nft-factory-groups.md":"fb09f2bb","examples_eosio.token.md":"c99cf15e","guides_basics_creating-a-wallet.md":"c22d2d4e","guides_basics_pushing-transactions.md":"971a602b","guides_basics_start-local-chain.md":"05160696","guides_docker_docker-image-usage.md":"4b6516d8","guides_docker_getting-started.md":"dde6f5b3","guides_docker_keosd.md":"4e382534","guides_docker_troubleshooting.md":"2d186c81","guides_game dev center_10. creating-token-factories.md":"9138da79","guides_smart contracts_6.examples.md":"5637d6b3","guides_docker_ultratest.md":"e517d447","guides_game dev center_8. create-compatibility-matrix.md":"c39e0f25","contracts_token contract_overview.md":"e24395b9","contracts_token contract_token actions_close.md":"9e9f58f8","contracts_token contract_token actions_issue.md":"60d53864","guides_uniq variants_validating-metadata.md":"525f0826","learn_block producers_launch procedures_synchronizing-with-genesis-node.md":"fba8be02","learn_blockchains_block-production.md":"026f8179","learn_blockchains_wallets.md":"9091be0a","learn_blockchains_consensus.md":"e276a94a","learn_ultra blockchain_2nd-hand-sale.md":"e52dd491","learn_ultra blockchain_transaction-queues-billing-and-rate-limiting.md":"24d83908","learn_ultra blockchain_account-types.md":"f503edfa","learn_ultra blockchain_key-differences.md":"adada2cf","learn_ultra blockchain_power-resource.md":"0840d990","learn_ultra blockchain_predicate-system.md":"f5612a81","learn_ultra blockchain_ram-policy.md":"44eb3f63","learn_ultra blockchain_rate-limiting.md":"0c48c78e","learn_ultra blockchain_transaction-failure-trace.md":"f29311d6","search.md":"4f93a49a","learn_index.md":"c15bd264","guides_uniq variants_updating-metadata.md":"504025a4","tools_contract-builder_index.md":"87c319f4","tools_index.md":"7f04464c","guides_docker_endpoint-usage.md":"e11de534","tools_smart-contract-toolkit_index.md":"44e78a6e","contracts_token contract_token actions_open.md":"9c5813d3","guides_docker_cleos.md":"bffdce92","guides_game dev center_2. editor-note.md":"f285c2f0","guides_wallet extension_custom-networks.md":"bc3424b1","guides_uniq avatar_clearavatar.md":"f2ab7d65","guides_uniq variants_uniq-metadata.md":"1e1e0fe6","guides_uwax_detect-wallet.md":"f2e0f6e4","learn_blockchains_accounts-and-permissions.md":"53dee84f","learn_blockchains_block-explorers.md":"cd1b105b","learn_block producers_launch procedures_setting-up-genesis-node.md":"72197c0a","guides_game dev center_3. getting-access.md":"bc1b599c","learn_blockchains_actions-and-transactions.md":"34151857","guides_game dev center_4. about-game-builds.md":"5c90c045","guides_game dev center_6. file-beam.md":"ddb8bff3","guides_nftapi_types.md":"39611641"}
