{"contracts_nft contract_nft actions_mgrfactories.md":"86dc2f66","contracts_nft contract_nft actions_cancelresell.md":"6f48a64d","contracts_nft contract_nft actions_clrmintst.md":"0c9cc19b","contracts_nft contract_nft actions_lckfactory.md":"8dc5ba40","contracts_nft contract_nft actions_limitmint.md":"4e709a13","contracts_kyc contract_kyc actions_removekycpro.md":"ed95e794","api_rest_get-abi.md":"4ba85951","api_rest_get-account.md":"8057b959","api_rest_get-block.md":"1b17fc62","api_rest_get-currency-balance.md":"97acd416","api_rest_get-info.md":"26e9cc78","api_rest_get-table-by-scope.md":"ce09da6a","api_rest_get-table-rows.md":"62762e4b","api_common-tables.md":"c732a777","contracts_kyc contract_kyc actions_registerkyc.md":"ee5e4271","contracts_nft contract_nft actions_addgrpfcts.md":"03f0a674","contracts_kyc contract_kyc actions_removekyc.md":"36a25867","contracts_kyc contract_kyc actions_togglekyc.md":"cf2b8aef","contracts_kyc contract_kyc-policy.md":"8dfb6a22","contracts_nft contract_nft actions_activers.md":"0194d4dc","contracts_nft contract_nft actions_buy.md":"debbf44c","contracts_nft contract_nft actions_authmint.b.md":"aaf64193","contracts_kyc contract_kyc actions_updatekyc.md":"a52b4f5b","contracts_kyc contract_kyc-tables.md":"ba1337a0","contracts_nft contract_nft actions_burn.md":"3aa3cfbb","contracts_nft contract_nft actions_authminter.md":"eb980fee","contracts_nft contract_nft actions_transfer.md":"7df55ce0","contracts_nft contract_nft actions_migration.md":"04c62605","contracts_nft contract_nft actions_recall.md":"1bb4fc8b","contracts_nft contract_nft actions_updategrp.md":"fb6ba0f4","contracts_nft contract_nft actions_create.b.md":"7a3e7a1b","contracts_nft contract_nft actions_creategrp.md":"7326935a","contracts_nft contract_nft actions_setstatus.md":"29f8912f","contracts_nft contract_nft actions_create.md":"ba568de2","contracts_nft contract_nft actions_issue.md":"b5400539","contracts_nft contract_nft actions_mgrnfts.md":"3eccffb4","contracts_nft contract_nft actions_settfflag.md":"3a834aad","contracts_system contract_system actions_newnonebact.md":"fef6cdaf","contracts_nft contract_nft actions_settknmeta.md":"68163e32","contracts_nft contract_nft-tables.md":"0a8ca0a4","contracts_nft contract_overview.md":"9d5a70f8","contracts_system contract_system actions_allowpred.md":"90d7026f","contracts_system contract_system actions_buyram.md":"cbdfa887","contracts_system contract_system actions_buyrambytes.md":"e03836bb","contracts_nft contract_nft-factory-groups.md":"a40fb7ea","contracts_system contract_system actions_delegatebw.md":"e3b6ce1f","contracts_system contract_system actions_newebact.md":"9280fe24","contracts_nft contract_nft actions_rmgrpfcts.md":"95c72cdd","contracts_nft contract_nft actions_deletegrp.md":"76a479a2","contracts_nft contract_nft actions_resell.md":"9cb3d2fe","api_index.md":"608eea37","contracts_nft contract_nft actions_setdflttkn.md":"97fb5e82","contracts_nft contract_nft actions_setconrecv.md":"57cc391e","contracts_nft contract_nft actions_setmeta.b.md":"3df86ee8","contracts_nft contract_nft actions_setmeta.md":"c081e9bd","contracts_nft contract_nft actions_setnftmgrflg.md":"8c911aef","contracts_system contract_system actions_refundram.md":"8308a0f6","contracts_nft contract_nft actions_issue.b.md":"dac20948","contracts_system contract_system actions_revokepred.md":"0fdaace7","contracts_system contract_eba-non-eba-accounts.md":"0d87ca79","contracts_system contract_system actions_undelegatebw.md":"321b4d34","contracts_system contract_data-structures-overview.md":"abb500a0","contracts_system contract_know-your-client.md":"bfbf4845","contracts_system contract_overview.md":"a1ced142","contracts_system contract_power-bandwidth-staking.md":"1e44d4c7","guides_basics_introduction.md":"72746c43","guides_basics_pushing-transactions.md":"51e7d23f","guides_basics_start-local-chain.md":"79f32fea","guides_docker_getting-started.md":"c28151da","guides_basics_using-cleos.md":"7ccd01cc","guides_docker_nodeos.md":"1a5e24a9","guides_docker_troubleshooting.md":"613c6646","guides_ultra specific_faucet.md":"8893d52d","contracts_token contract_token actions_issue.md":"40c1af60","guides_docker_obtaining-tokens-locally.md":"15813237","guides_cdt_compile-a-contract.md":"4a7c2a99","guides_docker_ultratest.md":"695ff979","examples_eosio.token.md":"f5f3438f","guides_ultra specific_request-fungible-token.md":"d54449f0","guides_docker_development-environment.md":"0aaa332f","guides_docker_docker-image-usage.md":"b40a635f","guides_docker_environments.md":"833196d2","guides_docker_endpoint-usage.md":"4e4363c4","contracts_system contract_predicate-system.md":"c9fc400c","contracts_system contract_ram-market.md":"36e52cb2","contracts_token contract_token actions_retire.md":"2f47eee0","contracts_token contract_token actions_close.md":"694d2617","contracts_token contract_token actions_open.md":"628eed18","contracts_token contract_token actions_transfer.md":"4989eb09","contracts_token contract_overview.md":"64c36888","contracts_token contract_token_tables.md":"f4b67cfe","contracts_index.md":"9f67c4fc","guides_basics_create-a-testnet-account.md":"354267ec","contracts_token contract_token actions_create.md":"20288025","guides_ultra specific_token-swap.md":"77a61f8c","guides_docker_index.md":"f84dcdbb","guides_docker_keosd.md":"ec10979b","guides_docker_building-smart-contracts.md":"19acf537","guides_basics_creating-a-wallet.md":"898cf078","guides_wallet extension_demo-application.md":"0a8ef2fb","guides_wallet extension_detect-wallet.md":"351cd1d3","guides_wallet extension_developer-resources.md":"d0472edf","guides_wallet extension_errors.md":"91c6206f","guides_wallet extension_events.md":"65cf5870","guides_wallet extension_import-private_key.md":"6715fb64","guides_wallet extension_installing-extension.md":"ba3d9507","guides_wallet extension_response-format.md":"5bd85615","guides_uniq variants_examples_on-issue.md":"fcc4fbb3","guides_index.md":"b601a296","learn_block producers_infrastructure_understanding-the-config.md":"6e61d9c9","guides_wallet extension_index.md":"ef1f903d","guides_wallet extension_signing-transaction.md":"63e2275f","learn_block producers_infrastructure_configuring-a-block-producer.md":"1f9b9e21","guides_cdt_index.md":"b6548529","learn_block producers_infrastructure_minimum-recommended-infrastructure.md":"413efbcb","learn_block producers_launch procedures_activating-the-chain.md":"bc08e01d","learn_block producers_infrastructure_block-producing-infrastructure.md":"982d37d1","learn_block producers_launch procedures_adding-new-producers.md":"0dbbcfff","learn_block producers_launch procedures_setting-up-genesis-node.md":"89f97947","guides_docker_cleos.md":"17e9c632","index.md":"8773a707","guides_wallet extension_signing_message.md":"c96f892d","learn_block producers_infrastructure_infrastructure-and-network-overview.md":"895dfc0e","learn_block producers_launch procedures_finishing-up.md":"864179ed","learn_block producers_infrastructure_templates-for-config.md":"f087c8a7","learn_block producers_launch procedures_core-concepts.md":"e4c8cdf2","learn_block producers_launch procedures_resigning-eosio-and-system-accounts.md":"fa998891","guides_cdt_create-a-contract.md":"18e9e51e","learn_block producers_launch procedures_registering-block-producers.md":"b8ad9fb9","guides_wallet extension_stablishing-connection.md":"c1ccb725","learn_block producers_maintenance_backup-and-recovery.md":"5ae545bb","learn_block producers_maintenance_launching-a-new-instance.md":"e450ecfd","learn_block producers_maintenance_multisignature-proposals.md":"c22fa25b","learn_blockchains_actions-and-transactions.md":"07c35059","learn_blockchains_accounts-and-permissions.md":"93c04589","learn_block producers_maintenance_upgrade-procedures.md":"7ab06679","learn_block producers_maintenance_system-contract-upgrade.md":"e86c0647","learn_blockchains_consensus.md":"2731f0ef","learn_blockchains_wallets.md":"c3361602","learn_ultra blockchain_2nd-hand-sale.md":"b3e58412","learn_blockchains_block-production.md":"9af25965","learn_ultra blockchain_account-types.md":"511f7a27","learn_ultra blockchain_key-differences.md":"afa71432","learn_ultra blockchain_transaction-limits-queues.md":"e7f98d84","guides_wallet extension_custom-networks.md":"a95f360e","learn_block producers_maintenance_account-administration.md":"fb3323d1","learn_ultra blockchain_power-resource.md":"0b282112","learn_ultra blockchain_predicate-system.md":"ff4733de","learn_block producers_launch procedures_synchronizing-with-genesis-node.md":"8c97a61f","search.md":"3245ef13","learn_ultra blockchain_ram-policy.md":"6c34d931","learn_ultra blockchain_rate-limiting.md":"daab4bec","learn_index.md":"4b04bb0b","tools_index.md":"a491d26e","learn_blockchains_block-explorers.md":"4422b398"}
